silver/__init__.py
silver/main.py
silver/silver.py
silver/src/Git.py
silver/src/__init__.py
silver/src/tests/__init__.py
silver/src/tests/test_add.py
silver/src/tests/test_clone.py
silver/src/tests/test_commit.py
silver/src/tests/test_privateClone.py
silver/src/tests/test_push.py
src/Git.py
src/__init__.py
src/tests/__init__.py
src/tests/test_add.py
src/tests/test_clone.py
src/tests/test_commit.py
src/tests/test_privateClone.py
src/tests/test_push.py
silverscript-1.0.12.dist-info/LICENSE
silverscript-1.0.12.dist-info/METADATA
silverscript-1.0.12.dist-info/WHEEL
silverscript-1.0.12.dist-info/entry_points.txt
silverscript-1.0.12.dist-info/top_level.txt
silverscript-1.0.12.dist-info/RECORD
