Metadata-Version: 2.1
Name: silverscript
Version: 1.0.12
Summary: Silver is a customizable python based shell prompt
Home-page: https://github.com/AugustinJose1221/silver
Author: Augustin Jose
Author-email: augustinjose1221@gmail.com
License: UNKNOWN
Platform: UNKNOWN
Classifier: Programming Language :: Python :: 3
Classifier: License :: OSI Approved :: GNU General Public License v3 or later (GPLv3+)
Classifier: Operating System :: OS Independent
Requires-Python: >=3.6
